LICENSE.txt
MANIFEST.in
README.md
pyproject.toml
setup.cfg
setup.py
IOS_SHOGUN/BufferBytes.py
IOS_SHOGUN/consoles.py
IOS_SHOGUN/shogun.py
IOS_SHOGUN.egg-info/PKG-INFO
IOS_SHOGUN.egg-info/SOURCES.txt
IOS_SHOGUN.egg-info/dependency_links.txt
IOS_SHOGUN.egg-info/top_level.txt