Metadata-Version: 2.1
Name: IOS-SHOGUN
Version: 1.0.2
Summary: shogun-python3 module 1.0 - updated: blocking byte buffers --+console logs + console_colors Reset the terminal color font + bufferState hunger state
Home-page: https://github.com/Atomicntege/IOS_SHOGUN/tree/Python_IOS_SHOGUN_Model
Author: AtomicJun
Author-email: q2372798989@163.com
Maintainer: IOS-SHOGUN-PublishingDepartment
License: UNKNOWN
Platform: all
Classifier: Programming Language :: Python :: 3
Classifier: License :: OSI Approved :: MIT License
Classifier: Operating System :: OS Independent
License-File: LICENSE.txt
